{"_type":"export","__export_format":4,"__export_date":"2020-03-13T21:58:57.212Z","__export_source":"insomnia.desktop.app:v7.1.1","resources":[{"_id":"req_4179b9908c064f15bd8196340969e13c","authentication":{"token":"{{ token  }}","type":"bearer"},"body":{"mimeType":"multipart/form-data","params":[{"description":"","id":"pair_5064969d4299428a8f53ca4a34b46649","name":"name","value":"Gabriel Teixeira Mesquita"},{"description":"","id":"pair_de367fdea6e848adb3dbf68dc3278343","name":"password","value":"123456"},{"description":"","id":"pair_36b6c6f41aec4ab28a393aeab0bf9474","name":"password_confirmation","value":"123456"},{"description":"","fileName":"/Users/gabriel-macbook/Desktop/rocketshoes/reactotron-example.png","id":"pair_d1cd29fc30c84b02b2ca5097c48d3ff4","name":"avatar","type":"file","value":""},{"description":"","id":"pair_9f4b8131cda1474f9c17ed6c87fbcbe3","name":"Accept","value":"application/json"}]},"created":1583944441146,"description":"","headers":[{"id":"pair_c68e0f179d154082ad70ca8ac818b81b","name":"Content-Type","value":"multipart/form-data"},{"description":"","id":"pair_edbfe84dfeff4f7f830c5a10e3317134","name":"Accept","value":"application/json"}],"isPrivate":false,"metaSortKey":-1583944441146,"method":"PUT","modified":1584050077866,"name":"Update","parameters":[],"parentId":"fld_de4ca0c0ff0a49589294536f3957dc9d","settingDisableRenderRequestBody":false,"settingEncodeUrl":true,"settingFollowRedirects":"global","settingRebuildPath":true,"settingSendCookies":true,"settingStoreCookies":true,"url":"{{ base_url  }}/profile","_type":"request"},{"_id":"fld_de4ca0c0ff0a49589294536f3957dc9d","created":1583944433104,"description":"","environment":{},"environmentPropertyOrder":null,"metaSortKey":-1583944433104,"modified":1583944433104,"name":"Profile","parentId":"wrk_7385a7fe8fb845a68588b273e06d9d4d","_type":"request_group"},{"_id":"wrk_7385a7fe8fb845a68588b273e06d9d4d","created":1583790696930,"description":"","modified":1583790696930,"name":"RSXP","parentId":null,"_type":"workspace"},{"_id":"req_9dff6a97cba744ab975948980a724e56","authentication":{"token":"{{ token  }}","type":"bearer"},"body":{"mimeType":"application/json","text":"{\n\t\"title\": \"Utilizando NodeJS para construir API`s seguras.\",\n  \"description\": \"Se você já buscou sobre as melhores linguagens back-end, este é para voce.\",\n  \"user_id\": 1,\n  \"section\": 3,\n\t\"color\": \"#715666\"\n}"},"created":1583863071361,"description":"","headers":[{"id":"pair_c8c7be0b6f1c408b835792fddca38895","name":"Content-Type","value":"application/json"},{"description":"","id":"pair_0a265308d11840af8567c93db5ef6e77","name":"Accept","value":"application/json"}],"isPrivate":false,"metaSortKey":-1583863071361,"method":"POST","modified":1584134532569,"name":"Create","parameters":[],"parentId":"fld_672e82d6f20c4525badfa931794cb6c0","settingDisableRenderRequestBody":false,"settingEncodeUrl":true,"settingFollowRedirects":"global","settingRebuildPath":true,"settingSendCookies":true,"settingStoreCookies":true,"url":"{{ base_url  }}/workshops","_type":"request"},{"_id":"fld_672e82d6f20c4525badfa931794cb6c0","created":1583863065543,"description":"","environment":{},"environmentPropertyOrder":null,"metaSortKey":-1583863065543,"modified":1583863065543,"name":"Workshops","parentId":"wrk_7385a7fe8fb845a68588b273e06d9d4d","_type":"request_group"},{"_id":"req_9c67d7b90c4d4374a8788abc2e89f66e","authentication":{"token":"{{ token  }}","type":"bearer"},"body":{"mimeType":"application/json","text":"{\n\t\"title\": \"Utilizando NodeJS para construir API`s seguras.\",\n  \"description\": \"Se você já buscou sobre as melhores linguagens back-end, este é para voce.\",\n  \"user_id\": 1,\n  \"section\": 3,\n\t\"color\": \"#000000\"\n}"},"created":1584050599228,"description":"","headers":[{"id":"pair_c8c7be0b6f1c408b835792fddca38895","name":"Content-Type","value":"application/json"},{"description":"","id":"pair_0a265308d11840af8567c93db5ef6e77","name":"Accept","value":"application/json"}],"isPrivate":false,"metaSortKey":-1583844995637.5,"method":"PUT","modified":1584134628793,"name":"Update","parameters":[],"parentId":"fld_672e82d6f20c4525badfa931794cb6c0","settingDisableRenderRequestBody":false,"settingEncodeUrl":true,"settingFollowRedirects":"global","settingRebuildPath":true,"settingSendCookies":true,"settingStoreCookies":true,"url":"{{ base_url  }}/workshops/1","_type":"request"},{"_id":"req_3064caf5a0114d6b93ac7c83bd1630b0","authentication":{"token":"{{ token  }}","type":"bearer"},"body":{},"created":1584051121626,"description":"","headers":[{"description":"","id":"pair_0a265308d11840af8567c93db5ef6e77","name":"Accept","value":"application/json"}],"isPrivate":false,"metaSortKey":-1583835957775.75,"method":"DELETE","modified":1584051125798,"name":"Delete","parameters":[],"parentId":"fld_672e82d6f20c4525badfa931794cb6c0","settingDisableRenderRequestBody":false,"settingEncodeUrl":true,"settingFollowRedirects":"global","settingRebuildPath":true,"settingSendCookies":true,"settingStoreCookies":true,"url":"{{ base_url  }}/workshops/1","_type":"request"},{"_id":"req_93d64e497f044fd6a2af735f4f98cd2e","authentication":{"token":"{{ token  }}","type":"bearer"},"body":{},"created":1583890007714,"description":"","headers":[{"description":"","id":"pair_0a265308d11840af8567c93db5ef6e77","name":"Accept","value":"application/json"}],"isPrivate":false,"metaSortKey":-1583826919914,"method":"GET","modified":1584135154026,"name":"List","parameters":[{"description":"","id":"pair_8bcd26a0b92140f0b2829058b180d6a2","name":"section","value":"3"}],"parentId":"fld_672e82d6f20c4525badfa931794cb6c0","settingDisableRenderRequestBody":false,"settingEncodeUrl":true,"settingFollowRedirects":"global","settingRebuildPath":true,"settingSendCookies":true,"settingStoreCookies":true,"url":"{{ base_url  }}/workshops","_type":"request"},{"_id":"req_6025ee07ac3142faacb726a56d7452fe","authentication":{"token":"{{ token  }}","type":"bearer"},"body":{},"created":1583942039516,"description":"","headers":[{"description":"","id":"pair_0a265308d11840af8567c93db5ef6e77","name":"Accept","value":"application/json"}],"isPrivate":false,"metaSortKey":-1583808844190.5,"method":"GET","modified":1583942042483,"name":"Show","parameters":[],"parentId":"fld_672e82d6f20c4525badfa931794cb6c0","settingDisableRenderRequestBody":false,"settingEncodeUrl":true,"settingFollowRedirects":"global","settingRebuildPath":true,"settingSendCookies":true,"settingStoreCookies":true,"url":"{{ base_url  }}/workshops/1","_type":"request"},{"_id":"req_7af545ead5c141548d4cb11241416a8e","authentication":{},"body":{"mimeType":"application/json","text":"{\n\t\"email\": \"gabrielteixeiramesquita@gmail.com\",\n\t\"password\": \"123456\"\n}"},"created":1583790768467,"description":"","headers":[{"id":"pair_76712cf2fc7648cdb810ba4705618533","name":"Content-Type","value":"application/json"},{"description":"","id":"pair_d6c1406e48d24c589ba6638b1ecf0d22","name":"Accept","value":"application/json"}],"isPrivate":false,"metaSortKey":-1583790768467,"method":"POST","modified":1583942735160,"name":"Sign In","parameters":[],"parentId":"fld_6fd1fe94e0e5483493eca79fdd0ca594","settingDisableRenderRequestBody":false,"settingEncodeUrl":true,"settingFollowRedirects":"global","settingRebuildPath":true,"settingSendCookies":true,"settingStoreCookies":true,"url":"{{ base_url  }}/sessions","_type":"request"},{"_id":"fld_6fd1fe94e0e5483493eca79fdd0ca594","created":1583790763137,"description":"","environment":{},"environmentPropertyOrder":null,"metaSortKey":-1583790763137,"modified":1583790763137,"name":"Authentication","parentId":"wrk_7385a7fe8fb845a68588b273e06d9d4d","_type":"request_group"},{"_id":"req_6fe6170cf1cb4071a9fe7b50ea1b3950","authentication":{},"body":{"mimeType":"application/json","text":"{\n\t\"email\": \"gabrielteixeiramesquita@gmail.com\"\n}"},"created":1583791359049,"description":"","headers":[{"id":"pair_76712cf2fc7648cdb810ba4705618533","name":"Content-Type","value":"application/json"},{"description":"","id":"pair_9154a6fb9234489388039629e838fbbd","name":"Accept","value":"application/json"}],"isPrivate":false,"metaSortKey":-1583047297307,"method":"POST","modified":1583880040801,"name":"Forgot password","parameters":[],"parentId":"fld_6fd1fe94e0e5483493eca79fdd0ca594","settingDisableRenderRequestBody":false,"settingEncodeUrl":true,"settingFollowRedirects":"global","settingRebuildPath":true,"settingSendCookies":true,"settingStoreCookies":true,"url":"{{ base_url  }}/forgot","_type":"request"},{"_id":"req_6f9fa3c3720440bab2dfca5a785e41f2","authentication":{},"body":{"mimeType":"application/json","text":"{\n\t\"token\": \"5742393219dcc4f754fb5921a6f43f183ccfe9c923f7b763\",\n\t\"password\": \"12345678\",\n\t\"password_confirmation\": \"12345678\"\n}"},"created":1583791673667,"description":"","headers":[{"id":"pair_76712cf2fc7648cdb810ba4705618533","name":"Content-Type","value":"application/json"},{"description":"","id":"pair_b1aba6796c1e465e83d993bf5e52de20","name":"Accept","value":"application/json"}],"isPrivate":false,"metaSortKey":-1582675561727,"method":"POST","modified":1583792101864,"name":"Reset password","parameters":[],"parentId":"fld_6fd1fe94e0e5483493eca79fdd0ca594","settingDisableRenderRequestBody":false,"settingEncodeUrl":true,"settingFollowRedirects":"global","settingRebuildPath":true,"settingSendCookies":true,"settingStoreCookies":true,"url":"{{ base_url  }}/reset","_type":"request"},{"_id":"env_6e121c9b706f61f0cf417ae2ad79fcf6a88577f1","color":null,"created":1583790697097,"data":{},"dataPropertyOrder":{},"isPrivate":false,"metaSortKey":1583790697097,"modified":1583790911451,"name":"Base Environment","parentId":"wrk_7385a7fe8fb845a68588b273e06d9d4d","_type":"environment"},{"_id":"jar_6e121c9b706f61f0cf417ae2ad79fcf6a88577f1","cookies":[],"created":1583790697101,"modified":1583790697101,"name":"Default Jar","parentId":"wrk_7385a7fe8fb845a68588b273e06d9d4d","_type":"cookie_jar"},{"_id":"env_c5327bc6999b4117b4a5558aeb2cd566","color":null,"created":1583790832387,"data":{"base_url":"http://localhost:3333","token":"eyJhbGciOiJIUzI1NiIsInR5cCI6IkpXVCJ9.eyJ1aWQiOjEsImlhdCI6MTU4Mzk0Mjc4MX0.dsLX4Epcr-75DIJfH-EfR-ctRKZTztSTyJdfjwEyvBE"},"dataPropertyOrder":{"&":["base_url","token"]},"isPrivate":false,"metaSortKey":1583790832387,"modified":1583942807733,"name":"dev","parentId":"env_6e121c9b706f61f0cf417ae2ad79fcf6a88577f1","_type":"environment"}]}